samplex/__init__.py
samplex/plotting.py
samplex/samplers.py
samplex/samplex.py
samplex/utils.py
samplex-0.0.2.dist-info/LICENSE
samplex-0.0.2.dist-info/METADATA
samplex-0.0.2.dist-info/WHEEL
samplex-0.0.2.dist-info/top_level.txt
samplex-0.0.2.dist-info/RECORD
